Metadata-Version: 1.0
Name: probability-func
Version: 0.1
Summary: Gaussian and Binomial distributions
Home-page: UNKNOWN
Author: Dimobi Stephanie
Author-email: stephaniedimobi@gmail.com
License: UNKNOWN
Platform: UNKNOWN
